[
{
"name": "Tomatoes",
"category": "vegetables",
"price": 25,
"quantity": 1000
},
{
"name": "Cucumbers",
"category": "vegetables",
"price": 20,
"quantity": 1000
},
{
"name": "Carrots",
"category": "vegetables",
"price": 15,
"quantity": 1000
},
{
"name": "Potatoes",
"category": "vegetables",
"price": 30,
"quantity": 1000
},
{
"name": "Bell Peppers",
"category": "vegetables",
"price": 35,
"quantity": 1000
},
{
"name": "Apples",
"category": "fruits",
"price": 30,
"quantity": 1000
},
{
"name": "Bananas",
"category": "fruits",
"price": 40,
"quantity": 1000
},
{
"name": "Oranges",
"category": "fruits",
"price": 45,
"quantity": 1000
},
{
"name": "Grapes",
"category": "fruits",
"price": 50,
"quantity": 1000
},
{
"name": "Strawberries",
"category": "fruits",
"price": 55,
"quantity": 1000
},
{
"name": "Raspberries",
"category": "berries",
"price": 40,
"quantity": 1000
},
{
"name": "Blueberries",
"category": "berries",
"price": 45,
"quantity": 1000
},
{
"name": "Blackberries",
"category": "berries",
"price": 50,
"quantity": 1000
},
{
"name": "Cranberries",
"category": "berries",
"price": 55,
"quantity": 1000
},
{
"name": "Raspberries",
"category": "berries",
"price": 60,
"quantity": 1000
}
]